{
    "<PAD>": 0,
    "<SOS>": 1,
    "<EOS>": 2,
    "<UNK>": 3,
    "0": 4,
    "1": 5,
    "2": 6,
    "3": 7,
    "4": 8,
    "5": 9,
    "6": 10,
    "7": 11,
    "8": 12,
    "9": 13,
    "b": 14,
    "bb": 15,
    "x": 16,
    "X": 17,
    "by": 18,
    "bcy": 19,
    "qy": 20,
    "dy": 21,
    "v": 22,
    "V": 23,
    "#": 24,
    "^": 25,
    "_": 26,
    "<": 27,
    ">": 28,
    ".": 29,
    "{": 30,
    "}": 31,
    "-": 32,
    "(": 33,
    ")": 34,
    "[": 35,
    "]": 36,
    "h": 37,
    "z1": 38,
    "z2": 39,
    "y": 40,
    "/": 41,
    ",": 42,
    "'": 43,
    "|": 44
}